ecs_files_composer/__init__.py
ecs_files_composer/aws_mgmt.py
ecs_files_composer/certificates_mgmt.py
ecs_files_composer/cli.py
ecs_files_composer/common.py
ecs_files_composer/ecs_files_composer.py
ecs_files_composer/envsubst.py
ecs_files_composer/files_mgmt.py
ecs_files_composer/input.py
ecs_files_composer/jinja2_filters/__init__.py
ecs_files_composer/jinja2_functions/__init__.py
ecs_files_composer/jinja2_functions/aws.py
ecs_files_composer-2.1.5.dist-info/AUTHORS.rst
ecs_files_composer-2.1.5.dist-info/LICENSE
ecs_files_composer-2.1.5.dist-info/METADATA
ecs_files_composer-2.1.5.dist-info/WHEEL
ecs_files_composer-2.1.5.dist-info/entry_points.txt
ecs_files_composer-2.1.5.dist-info/RECORD
