Metadata-Version: 2.1
Name: ecs_files_composer
Version: 2.1.5
Summary: Files and configuration handler to inject configuration files into volumes for ECS containers
License: MPL-2.0
Keywords: aws,ecs,k8s,secrets
Author: John Preston
Author-email: john@compose-x.io
Requires-Python: >=3.8,<4.0
Classifier: Development Status :: 5 - Production/Stable
Classifier: Intended Audience :: Developers
Classifier: Intended Audience :: Information Technology
Classifier: Intended Audience :: System Administrators
Classifier: License :: OSI Approved
Classifier: License :: OSI Approved :: Mozilla Public License 2.0 (MPL 2.0)
Classifier: Natural Language :: English
Classifier: Programming Language :: Python :: 3
Classifier: Programming Language :: Python :: 3.8
Classifier: Programming Language :: Python :: 3.9
Classifier: Programming Language :: Python :: 3.10
Classifier: Programming Language :: Python :: 3.11
Classifier: Programming Language :: Python :: 3.12
Requires-Dist: Jinja2 (>=3.1.2,<4.0.0)
Requires-Dist: PyYAML (>=6.0,<7.0)
Requires-Dist: aws-cfn-custom-resource-resolve-parser (>=0.3.0,<0.4.0)
Requires-Dist: boto3 (>=1.28,<2.0)
Requires-Dist: compose-x-common (>=1.3,<2.0)
Requires-Dist: dacite (>=1.8.1,<2.0.0)
Requires-Dist: flatdict (>=4.0.1,<5.0.0)
Requires-Dist: jsonschema (>=4.17,<5.0)
Requires-Dist: pyOpenSSL (>=23.2,<24.0)
Requires-Dist: requests (>=2.31,<3.0)
